KratosMultiphysics/.libs/KratosFemToDemApplication.pyd
KratosMultiphysics/FemToDemApplication/FEMDEMParticleCreatorDestructor.py
KratosMultiphysics/FemToDemApplication/FemDemDynamicSolver.py
KratosMultiphysics/FemToDemApplication/FemDemMechanicalSolver.py
KratosMultiphysics/FemToDemApplication/FemDemStaticSolver.py
KratosMultiphysics/FemToDemApplication/MainCoupling2WayFemDem.py
KratosMultiphysics/FemToDemApplication/MainCouplingFemDem.py
KratosMultiphysics/FemToDemApplication/MainCouplingFemDemSubstepping.py
KratosMultiphysics/FemToDemApplication/MainCouplingFemDemSubstepping_for_PFEM_coupling.py
KratosMultiphysics/FemToDemApplication/MainCouplingFemDem_for_PFEM_coupling.py
KratosMultiphysics/FemToDemApplication/MainCouplingPfemFemDem.py
KratosMultiphysics/FemToDemApplication/MainCouplingPfemFemDemAitken.py
KratosMultiphysics/FemToDemApplication/MainCouplingPfemFemDemAitkenSubstepping.py
KratosMultiphysics/FemToDemApplication/MainCouplingPfemFemDemSubstepping.py
KratosMultiphysics/FemToDemApplication/MainDEM_for_coupling.py
KratosMultiphysics/FemToDemApplication/MainFEM_for_PFEM_coupling.py
KratosMultiphysics/FemToDemApplication/MainFEM_for_coupling.py
KratosMultiphysics/FemToDemApplication/MainFemDem.py
KratosMultiphysics/FemToDemApplication/MainPFEM_for_coupling.py
KratosMultiphysics/FemToDemApplication/MainSolidFEM.py
KratosMultiphysics/FemToDemApplication/__init__.py
KratosMultiphysics/FemToDemApplication/apply_normal_load_table_process.py
KratosMultiphysics/FemToDemApplication/apply_scalar_constraint_table_process.py
KratosMultiphysics/FemToDemApplication/apply_vector_constraint_table_process.py
KratosMultiphysics/FemToDemApplication/assign_modulus_and_direction_to_conditions_process.py
KratosMultiphysics/FemToDemApplication/assign_modulus_and_direction_to_nodes_process.py
KratosMultiphysics/FemToDemApplication/assign_scalar_to_conditions_process.py
KratosMultiphysics/FemToDemApplication/assign_scalar_to_elements_process.py
KratosFemToDemApplication-10.2.3.dist-info/METADATA
KratosFemToDemApplication-10.2.3.dist-info/WHEEL
KratosFemToDemApplication-10.2.3.dist-info/top_level.txt
KratosFemToDemApplication-10.2.3.dist-info/RECORD
